AlleleFinder-0.4.7.data/scripts/allele_translate_reduce.py
AlleleFinder-0.4.7.data/scripts/allele_updater.py
AlleleFinder-0.4.7.data/scripts/profile_reduce.py
AlleleFinder-0.4.7.data/scripts/split_db.py
AlleleFinder-0.4.7.data/scripts/stec.py
allele_tools/__init__.py
allele_tools/allele_profiler.py
allele_tools/allele_translate_reduce.py
allele_tools/allele_updater.py
allele_tools/methods.py
allele_tools/profile_reduce.py
allele_tools/split_db.py
allele_tools/stec.py
allele_tools/version.py
tests/__init__.py
tests/test_0_profile_reduce.py
tests/test_1_allele_translate_reduce.py
tests/test_2_allele_updater.py
tests/test_3_stec_profile_reduce.py
tests/test_4_stec_allele_translate_reduce.py
tests/test_5_stec_allele_find.py
tests/test_6_stec_aa_allele_find.py
tests/test_7_stec_allele_split.py
tests/test_8_stec_allele_concatenate.py
tests/test_9_stec_allele_translate_find.py
tests/test_split_db.py
AlleleFinder-0.4.7.dist-info/LICENSE
AlleleFinder-0.4.7.dist-info/METADATA
AlleleFinder-0.4.7.dist-info/WHEEL
AlleleFinder-0.4.7.dist-info/entry_points.txt
AlleleFinder-0.4.7.dist-info/top_level.txt
AlleleFinder-0.4.7.dist-info/RECORD
