Metadata-Version: 2.1
Name: AlleleFinder
Version: 0.4.7
Home-page: https://github.com/OLC-Bioinformatics/AlleleFinder
Author: Adam Koziol
Author-email: adam.koziol@inspection.gc.ca
Classifier: Intended Audience :: Science/Research
Classifier: License :: OSI Approved :: MIT License
Classifier: Programming Language :: Python :: 3.9
Classifier: Development Status :: 5 - Production/Stable
Classifier: Topic :: Scientific/Engineering :: Bio-Informatics
License-File: LICENSE
Requires-Dist: biopython ==1.81
Requires-Dist: click ==8.1.3
Requires-Dist: coloredlogs ==15.0.1
Requires-Dist: genemethods ==0.0.0.61
Requires-Dist: geneseekr ==0.5.0
Requires-Dist: genewrappers ==0.0.0.10
Requires-Dist: numpy ==1.26.4
Requires-Dist: OLCTools ==1.3.5
Requires-Dist: psutil ==5.9.4
Requires-Dist: pytest ==7.2.1
Requires-Dist: pytest-cov ==4.0.0
Requires-Dist: seaborn ==0.12.2
Requires-Dist: setuptools ==69.0.3
Requires-Dist: xlsxwriter ==3.0.2
